mocksign/__init__.py
mocksign/filter.py
mocksign/mocksign.py
mocksign/pdf.py
mocksign/signature.py
mocksign/signatures/Signature 1.png
mocksign/signatures/Signature 2.png
mocksign/signatures/Signature 3.png
mocksign/signatures/Signature 4.png
mocksign/signatures/Signature 5.png
mocksign/utils.py
mocksign-0.1.2.dist-info/LICENSE
mocksign-0.1.2.dist-info/METADATA
mocksign-0.1.2.dist-info/WHEEL
mocksign-0.1.2.dist-info/entry_points.txt
mocksign-0.1.2.dist-info/RECORD
