Metadata-Version: 2.1
Name: mocksign
Version: 0.1.2
Summary: Easily simulate printing, hand-signing and scanning of documents, inspired by FalsiSign.
Home-page: https://github.com/srwi/mocksign
License: MIT
Author: Stephan Rumswinkel
Author-email: 17520641+srwi@users.noreply.github.com
Requires-Python: >=3.8,<4.0
Classifier: License :: OSI Approved :: MIT License
Classifier: Programming Language :: Python :: 3
Classifier: Programming Language :: Python :: 3.8
Classifier: Programming Language :: Python :: 3.9
Classifier: Programming Language :: Python :: 3.10
Classifier: Programming Language :: Python :: 3.11
Classifier: Programming Language :: Python :: 3.12
Requires-Dist: FreeSimpleGUI (==5.1.1)
Requires-Dist: Pillow (==10.4.0)
Requires-Dist: PyMuPDF (==1.24.9)
Requires-Dist: opencv-python (==4.10.0.84)
Project-URL: Repository, https://github.com/srwi/mocksign
